cist/__init__.py
cist/objects.py
cist/schedule.py
cist/transport.py
cist/utils.py
cist-0.1.0.dist-info/METADATA
cist-0.1.0.dist-info/WHEEL
cist-0.1.0.dist-info/RECORD
