Metadata-Version: 2.1
Name: cist
Version: 0.1.0
Summary: CIST NURE API implementation
Home-page: https://github.com/WWFyb3NsYXYg/python-cist
Keywords: nure,cist
Author: Yaroslav WWFyb3NsYXYg
Author-email: minestrim13@gmail.com
Requires-Python: >=3.10,<4.0
Classifier: Programming Language :: Python :: 3
Classifier: Programming Language :: Python :: 3.10
Classifier: Programming Language :: Python :: 3.11
Classifier: Programming Language :: Python :: 3.12
Requires-Dist: requests (>=2.22,<3.0)
